streamlit_component_fill_square_cropper101/__init__.py
streamlit_component_fill_square_cropper101-0.0.6.dist-info/METADATA
streamlit_component_fill_square_cropper101-0.0.6.dist-info/WHEEL
streamlit_component_fill_square_cropper101-0.0.6.dist-info/top_level.txt
streamlit_component_fill_square_cropper101-0.0.6.dist-info/RECORD
