Metadata-Version: 2.1
Name: streamlit_component_fill_square_cropper101
Version: 0.0.6
Summary: streamlit_component_fill_square_cropper, adds a filler when needed of the avg color pixel.
Home-page: https://github.com/webdevserv/streamlit_component_fill_square_cropper101
Author: Idoia Lertxundi
Author-email: idoiagoikoa@gmail.com
Requires-Python: >=3.6
Requires-Dist: Pillow
Requires-Dist: numpy
Requires-Dist: streamlit
